{"State.51b94490-5f20-470f-a382-2b702f240c55": {"id": "51b94490-5f20-470f-a382-2b702f240c55", "created_at": "2024-07-15T02:49:51.240320", "updated_at": "2024-07-15T02:49:51.240325", "name": "California", "__class__": "State"}, "State.bf19b8d2-9d8a-4ad1-949f-a1600af27d06": {"id": "bf19b8d2-9d8a-4ad1-949f-a1600af27d06", "created_at": "2024-07-15T02:49:51.240738", "updated_at": "2024-07-15T02:49:51.240740", "name": "Arizona", "__class__": "State"}, "Place.6eb1f373-e3d9-4dbf-8bf6-c526c0a10a37": {"id": "6eb1f373-e3d9-4dbf-8bf6-c526c0a10a37", "created_at": "2024-07-15T02:49:51.242720", "updated_at": "2024-07-15T02:49:51.242724", "city_id": "0001", "user_id": "0001", "name": "My little house", "number_rooms": 4, "number_bathrooms": 2, "max_guest": 10, "price_by_night": 300, "latitude": 37.773972, "longitude": -122.431297, "__class__": "Place"}}